git_nit/__init__.py
git_nit/cmd.py
git_nit/tests/__init__.py
git_nit/tests/test_parse_review_id.py
git_nit-1.0.0.dist-info/DESCRIPTION.rst
git_nit-1.0.0.dist-info/METADATA
git_nit-1.0.0.dist-info/RECORD
git_nit-1.0.0.dist-info/WHEEL
git_nit-1.0.0.dist-info/entry_points.txt
git_nit-1.0.0.dist-info/metadata.json
git_nit-1.0.0.dist-info/pbr.json
git_nit-1.0.0.dist-info/top_level.txt
