Metadata-Version: 2.0
Name: git-nit
Version: 1.0.0
Summary: Tool to simplify making minor changes to patches in gerrit
Home-page: https://github.com/dhellmann/git-nit
Author: OpenStack
Author-email: openstack-dev@lists.openstack.org
License: Apache License (2.0)
Keywords: git gerrit review
Platform: UNKNOWN
Classifier: Programming Language :: Python :: 2
Classifier: Programming Language :: Python :: 3
Classifier: Programming Language :: Python
Classifier: Development Status :: 5 - Production/Stable
Classifier: Environment :: Console
Classifier: Environment :: OpenStack
Classifier: Intended Audience :: Developers
Classifier: Intended Audience :: Information Technology
Classifier: License :: OSI Approved :: Apache Software License
Classifier: Operating System :: OS Independent
Requires-Dist: requests (>=1.1)
Requires-Dist: six
